info_cluster/__init__.py
info_cluster/info_cluster.py
info_cluster/test_info_cluster.py
info_cluster-0.7.dist-info/METADATA
info_cluster-0.7.dist-info/WHEEL
info_cluster-0.7.dist-info/top_level.txt
info_cluster-0.7.dist-info/RECORD
