Metadata-Version: 2.1
Name: info-cluster
Version: 0.7
Summary: a hierachical clustering algorithm based on information theory
Home-page: https://github.com/zhaofeng-shu33/info_cluster_python_binding
Author: zhaofeng-shu33
Author-email: 616545598@qq.com
License: Apache License Version 2.0
Platform: UNKNOWN
Classifier: Programming Language :: Python :: 3
Requires-Dist: numpy
Requires-Dist: scikit-learn
Requires-Dist: ete3
Requires-Dist: networkx
Requires-Dist: pspartition
